.travis.yml
README.md
setup.py
needystates/__init__.py
needystates/exceptions.py
needystates/handler.py
needystates/need.py
needystates/need_filters.py
needystates/needprocessor.py
needystates/operations.py
needystates/state.py
needystates.egg-info/PKG-INFO
needystates.egg-info/SOURCES.txt
needystates.egg-info/dependency_links.txt
needystates.egg-info/top_level.txt
needystates/tests/__init__.py
needystates/tests/test_needfilters.py
needystates/tests/test_needprocessor.py
needystates/tests/test_needs.py
needystates/tests/test_states.py