Metadata-Version: 1.0
Name: needystates
Version: 0.4.0
Summary: UNKNOWN
Home-page: UNKNOWN
Author: Grayson Head
Author-email: grayson@graysonhead.net
License: GPL V3
Platform: UNKNOWN
